splitter/__init__.py
splitter/errors.py
splitter/file.py
splitter/file_handler.py
splitter/interfaces.py
splitter/langchain.py
splitter/py.typed
splitter/eml/__init__.py
splitter/eml/eml_handler.py
splitter/image/__init__.py
splitter/image/image.py
splitter/image/image_handler.py
splitter/image/tiff_handler.py
splitter/mime_reader/__init__.py
splitter/mime_reader/magic_mime_reader.py
splitter/mime_reader/mime_reader.py
splitter/mime_reader/mime_reader_interface.py
splitter/pdf/__init__.py
splitter/pdf/pdf_handler.py
axa_fr_splitter-1.0.0.dist-info/METADATA
axa_fr_splitter-1.0.0.dist-info/WHEEL
axa_fr_splitter-1.0.0.dist-info/licenses/LICENSE
axa_fr_splitter-1.0.0.dist-info/RECORD
