Metadata-Version: 2.3
Name: axa-fr-splitter
Version: 1.0.0
Summary: This package splits PDF and TIFF files into separate PNGs and extracts text from input files.
Project-URL: Repository, https://github.com/AxaFrance/axa-fr-splitter
Project-URL: Issues, https://github.com/AxaFrance/axa-fr-splitter/issues
Author-email: Dhia Hmila <dhia.hmila@axa.fr>, Guillaume Chervet <guillaume.chervet@axa.fr>, Hicham Dakhli <hicham.dakhli@axa.fr>
License: MIT License
License-File: LICENSE
Keywords: doc-proc,pdf,tif,tiff,word
Classifier: Intended Audience :: Developers
Classifier: License :: OSI Approved :: MIT License
Classifier: Programming Language :: Python :: 3
Classifier: Programming Language :: Python :: 3.10
Classifier: Programming Language :: Python :: 3.11
Classifier: Programming Language :: Python :: 3.12
Requires-Python: >=3.10
Requires-Dist: returns>=0.20.0
Provides-Extra: eml
Requires-Dist: eml-parser>=1.17.5; extra == 'eml'
Provides-Extra: image
Requires-Dist: opencv-python-headless>=4.7; extra == 'image'
Provides-Extra: langchain
Requires-Dist: langchain-community>=0.3.0; extra == 'langchain'
Requires-Dist: langchain-core>=0.3.0; extra == 'langchain'
Provides-Extra: magic
Requires-Dist: python-magic>=0.4.27; extra == 'magic'
Provides-Extra: pdf
Requires-Dist: pymupdf>=1.21.1; extra == 'pdf'
Provides-Extra: tests
Requires-Dist: eml-parser>=1.17.5; extra == 'tests'
Requires-Dist: langchain-community>=0.3.0; extra == 'tests'
Requires-Dist: langchain-core>=0.3.0; extra == 'tests'
Requires-Dist: opencv-python-headless>=4.7; extra == 'tests'
Requires-Dist: pdfminer-six>=20231228; extra == 'tests'
Requires-Dist: pymupdf>=1.21.1; extra == 'tests'
Requires-Dist: python-magic>=0.4.27; extra == 'tests'
